tools/__init__.py
tools/aoc.py
tools/aoc_ocr.py
tools/coordinate.py
tools/daemon.py
tools/datafiles.py
tools/grid.py
tools/int_seq.py
tools/irc.py
tools/itertools.py
tools/lists.py
tools/math.py
tools/schedule.py
tools/simplesocket.py
tools/stopwatch.py
tools/tools.py
tools/trees.py
tools/visualization.py
shs_tools-0.4.0.dist-info/LICENSE
shs_tools-0.4.0.dist-info/METADATA
shs_tools-0.4.0.dist-info/WHEEL
shs_tools-0.4.0.dist-info/top_level.txt
shs_tools-0.4.0.dist-info/RECORD
